_yoyo_cli/__init__.py
_yoyo_cli/cli.py
_yoyo_cli/core.py
_yoyo_cli/templates/__init__.py
_yoyo_cli/templates/bot/.env.dist
_yoyo_cli/templates/bot/.gitignore
_yoyo_cli/templates/bot/__init__.py
_yoyo_cli/templates/bot/config.py
_yoyo_cli/templates/bot/models/__init__.py
_yoyo_cli/templates/bot/routers/__init__.py
_yoyo_cli/templates/bot/routers/base/__init__.py
_yoyo_cli/templates/bot/routers/base/handlers/__init__.py
_yoyo_cli/templates/bot/routers/base/middlewares/__init__.py
_yoyo_cli/templates/bot/routers/base/scripts/__init__.py
_yoyo_cli/templates/bot/routers/middlewares/__init__.py
_yoyo_cli/templates/bot/scripts/__init__.py
_yoyo_cli/templates/bot/utils/__init__.py
_yoyo_cli/templates/bot/utils/menu.py
_yoyo_cli/templates/bot/utils/scheduler/__init__.py
_yoyo_cli/templates/model/__init__.py
_yoyo_cli/templates/model/model.py
_yoyo_cli/templates/project/.gitignore
_yoyo_cli/templates/project/__init__.py
_yoyo_cli/templates/project/main.py
_yoyo_cli/templates/project/requirements.txt
_yoyo_cli/templates/project/tgbot/__init__.py
_yoyo_cli/templates/project/tgbot/bot.py
_yoyo_cli/templates/project/tgbot/bots/__init__.py
_yoyo_cli/templates/project/tgbot/data/__init__.py
_yoyo_cli/templates/project/tgbot/data/texts.py
_yoyo_cli/templates/project/tgbot/data/web_apps.py
_yoyo_cli/templates/project/tgbot/models/__init__.py
_yoyo_cli/templates/router/__init__.py
_yoyo_cli/templates/router/handlers/__init__.py
_yoyo_cli/templates/router/middlewares/__init__.py
_yoyo_cli/templates/router/routers/__init__.py
_yoyo_cli/templates/router/scripts/__init__.py
yoyo/__init__.py
yoyo/logger.py
yoyo/tools.py
yoyo/handlers/__init__.py
yoyo/keyboards/__init__.py
yoyo/middlewares/__init__.py
yoyo/models/__init__.py
yoyogram-0.0.8.dist-info/licenses/LICENSE
yoyogram-0.0.8.dist-info/METADATA
yoyogram-0.0.8.dist-info/WHEEL
yoyogram-0.0.8.dist-info/entry_points.txt
yoyogram-0.0.8.dist-info/top_level.txt
yoyogram-0.0.8.dist-info/RECORD
