Metadata-Version: 2.4
Name: yoyogram
Version: 0.0.8
Summary: The framework to ease the work with huge projects with aiogram
Author: dhmmmhb
Classifier: Programming Language :: Python :: 3
Classifier: License :: OSI Approved :: MIT License
Requires-Python: >=3.7
License-File: LICENSE
Requires-Dist: aiogram
Requires-Dist: redis
Requires-Dist: environs
Requires-Dist: aiosqlite
Requires-Dist: APScheduler
Requires-Dist: rich
Dynamic: author
Dynamic: classifier
Dynamic: description-content-type
Dynamic: license-file
Dynamic: requires-dist
Dynamic: requires-python
Dynamic: summary
